schedule_filter/__init__.py
schedule_filter-0.2.1.dist-info/LICENSE
schedule_filter-0.2.1.dist-info/METADATA
schedule_filter-0.2.1.dist-info/WHEEL
schedule_filter-0.2.1.dist-info/top_level.txt
schedule_filter-0.2.1.dist-info/RECORD
