Metadata-Version: 2.1
Name: schedule-filter
Version: 0.2.1
Summary: Create advanced dbader/schedule with schedule-filters
Home-page: https://github.com/ruru4143/schedule_filter
Author: ruru4143
Author-email: pypi@ruru.pw
License: GPLv3
Download-URL: https://github.com/ruru4143/schedule_filter/0.2.1
Keywords: schedule,periodic,jobs,scheduling,clockwork,cron,scheduler,job scheduling
Platform: UNKNOWN
Classifier: Intended Audience :: Developers
Classifier: License :: OSI Approved :: GNU General Public License v3 (GPLv3)
Classifier: Programming Language :: Python
Classifier: Programming Language :: Python :: 3
Classifier: Programming Language :: Python :: 2.7
Classifier: Programming Language :: Python :: 3.5
Classifier: Programming Language :: Python :: 3.6
Classifier: Programming Language :: Python :: 3.7
Classifier: Natural Language :: English
